spyhunt/__init__.py
spyhunt/__main__.py
spyhunt/dnsparser.py
spyhunt/install.py
spyhunt/spyhunt.py
spyhunt/modules/__init__.py
spyhunt/modules/actuator_scan.py
spyhunt/modules/advanced_scanners.py
spyhunt/modules/favicon.py
spyhunt/modules/heap_dump.py
spyhunt/modules/heapdump_scan.py
spyhunt/modules/jwt_analyzer.py
spyhunt/modules/security_utils.py
spyhunt/modules/ss3sec.py
spyhunt/modules/ssl_sec.py
spyhunt/modules/sub_output.py
spyhunt/modules/user_agents.py
spyhunt/modules/useragent_list.py
spyhunt/payloads/api-endpoints.txt
spyhunt/payloads/bypasses.txt
spyhunt/payloads/proxies.txt
spyhunt/payloads/sqli.txt
spyhunt/payloads/ssrf_params.txt
spyhunt/payloads/traversal.txt
spyhunt/payloads/xss.txt
spyhunt/scripts/certsh.sh
spyhunt/scripts/shodanscan.sh
spyhunt/scripts/spotter.sh
spyhunt/scripts/waybackmachina.py
spyhunt/tools/assetfinder
spyhunt/tools/f5bigip_scanner.py
spyhunt/tools/pathhunt.py
spyhunt/tools/smuggler/LICENSE
spyhunt/tools/smuggler/README.md
spyhunt/tools/smuggler/smuggler.py
spyhunt/tools/smuggler/configs/default.py
spyhunt/tools/smuggler/configs/doubles.py
spyhunt/tools/smuggler/configs/exhaustive.py
spyhunt/tools/smuggler/payloads/README.md
spyhunt/tools/whatwaf/Dockerfile
spyhunt/tools/whatwaf/LICENSE.md
spyhunt/tools/whatwaf/README.md
spyhunt/tools/whatwaf/bootstrap.sh
spyhunt/tools/whatwaf/install_helper.sh
spyhunt/tools/whatwaf/requirements.txt
spyhunt/tools/whatwaf/setup.py
spyhunt/tools/whatwaf/whatwaf
spyhunt/tools/whatwaf/content/__init__.py
spyhunt/tools/whatwaf/content/files/auth.key
spyhunt/tools/whatwaf/content/files/default_payloads.lst
spyhunt/tools/whatwaf/content/files/post_strings.lst
spyhunt/tools/whatwaf/content/files/teapot.txt
spyhunt/tools/whatwaf/content/files/user_agents.txt
spyhunt/tools/whatwaf/content/plugins/360.py
spyhunt/tools/whatwaf/content/plugins/__init__.py
spyhunt/tools/whatwaf/content/plugins/aesecure.py
spyhunt/tools/whatwaf/content/plugins/airlock.py
spyhunt/tools/whatwaf/content/plugins/akamai.py
spyhunt-4.0.3.dist-info/licenses/LICENSE
spyhunt-4.0.3.dist-info/METADATA
spyhunt-4.0.3.dist-info/WHEEL
spyhunt-4.0.3.dist-info/entry_points.txt
spyhunt-4.0.3.dist-info/top_level.txt
spyhunt-4.0.3.dist-info/RECORD
