Metadata-Version: 2.4
Name: spyhunt
Version: 4.0.3
Summary: A comprehensive network scanning and vulnerability assessment tool designed for security professionals
Author-email: Mmdrza <pymmdrza@gmail.com>
Maintainer-email: Mmdrza <pymmdrza@gmail.com>
License-Expression: MIT
Project-URL: Homepage, https://spyhunt.readthedocs.io/
Project-URL: Documentation, https://spyhunt.readthedocs.io/en/latest/
Project-URL: Repository, https://github.com/Pymmdrza/spyhunt
Project-URL: Bug Reports, https://github.com/Pymmdrza/spyhunt/issues
Keywords: security,vulnerability,scanner,penetration-testing,reconnaissance,bug-bounty,web-security,network-security,subdomain-enumeration,vulnerability-scanner,security-tools,pentesting,ethical-hacking,infosec,cybersecurity
Classifier: Development Status :: 5 - Production/Stable
Classifier: Intended Audience :: Information Technology
Classifier: Intended Audience :: System Administrators
Classifier: Intended Audience :: Developers
Classifier: Topic :: Security
Classifier: Topic :: System :: Networking
Classifier: Topic :: Internet :: WWW/HTTP
Classifier: Programming Language :: Python :: 3
Classifier: Programming Language :: Python :: 3.7
Classifier: Programming Language :: Python :: 3.8
Classifier: Programming Language :: Python :: 3.9
Classifier: Programming Language :: Python :: 3.10
Classifier: Programming Language :: Python :: 3.11
Classifier: Operating System :: OS Independent
Classifier: Operating System :: POSIX :: Linux
Classifier: Operating System :: MacOS
Classifier: Environment :: Console
Requires-Python: >=3.7
License-File: LICENSE
Requires-Dist: colorama
Requires-Dist: requests
Requires-Dist: shodan
Requires-Dist: mmh3
Requires-Dist: PyExecJS
Requires-Dist: python3-nmap
Requires-Dist: beautifulsoup4
Requires-Dist: fake-useragent
Requires-Dist: googlesearch-python
Requires-Dist: alive-progress
Requires-Dist: python-whois
Requires-Dist: aiohttp
Requires-Dist: dnspython
Requires-Dist: waybackpy
Requires-Dist: ratelimit
Requires-Dist: pyjwt
Requires-Dist: boto3
Requires-Dist: ipinfo
Requires-Dist: tqdm
Requires-Dist: impacket
Requires-Dist: PySocks
Requires-Dist: urllib3
Provides-Extra: dev
Requires-Dist: pytest>=7.0.0; extra == "dev"
Requires-Dist: pytest-cov>=3.0.0; extra == "dev"
Requires-Dist: black>=22.0.0; extra == "dev"
Requires-Dist: flake8>=4.0.0; extra == "dev"
Requires-Dist: mypy>=0.950; extra == "dev"
Dynamic: license-file
